amlr/amlr.py
amlr/templates/.index.html.swp
amlr/templates/background.jpeg
amlr/templates/config.tmp
amlr/templates/config_page.html
amlr/templates/config_table_tbodyb.css
amlr/templates/config_table_tbodyf.css
amlr/templates/config_table_tbodyh.css
amlr/templates/config_table_tfootb.css
amlr/templates/config_table_tfootf.css
amlr/templates/config_table_tfooth.css
amlr/templates/config_table_theadb.css
amlr/templates/config_table_theadf.css
amlr/templates/config_table_theadh.css
amlr/templates/config_tablef.css
amlr/templates/config_tableh.css
amlr/templates/index.css
amlr/templates/index.html
amlr/templates/templates.dat
amlr/templates/images/SmallLogo.png
amlr/templates/images/blank.png
amlr/templates/images/logo.png
amlr-0.4.1.dist-info/METADATA
amlr-0.4.1.dist-info/WHEEL
amlr-0.4.1.dist-info/top_level.txt
amlr-0.4.1.dist-info/RECORD
