Metadata-Version: 2.1
Name: amlr
Version: 0.4.1
Summary: amlr - Auto Machine Learning Report
Home-page: https://github.com/dbranquinho/amlr
Author: Delermando Branquinho Filho
Author-email: delermando@gmail.com
License: MIT
Platform: UNKNOWN
Requires-Dist: matplotlib (>=3.3.4)
Requires-Dist: numpy (>=1.19.2)
Requires-Dist: pandas (>=1.1.3)
Requires-Dist: seaborn (>=0.11.1)
Requires-Dist: utils (>=1.0.1)
Requires-Dist: pywpb (>=0.1.7)
Requires-Dist: h2o (>=3.32.0.4)
Requires-Dist: statsmodels (>=0.12.2)
Requires-Dist: scikit-learn (>=0.24.1)
Requires-Dist: tqdm (>=4.58.0)
Requires-Dist: yellowbrick (>=1.3)
Requires-Dist: opencv-python (>=4.5.1.48)
Requires-Dist: pycm (>=3.0)
